pywe_ticket/__init__.py
pywe_ticket/baseticket.py
pywe_ticket/pyweticket.py
pywe_ticket-1.1.1.dist-info/METADATA
pywe_ticket-1.1.1.dist-info/RECORD
pywe_ticket-1.1.1.dist-info/WHEEL
pywe_ticket-1.1.1.dist-info/top_level.txt
